KrxRank/__init__.py
KrxRank/etc.py
KrxRank/krx.py
KrxRank/rank.py
KrxRank-1.0.1.dist-info/LICENSE
KrxRank-1.0.1.dist-info/METADATA
KrxRank-1.0.1.dist-info/WHEEL
KrxRank-1.0.1.dist-info/top_level.txt
KrxRank-1.0.1.dist-info/RECORD
