Metadata-Version: 2.1
Name: KrxRank
Version: 1.0.1
Summary: KRX 정보데이터시스템 순위 통계 데이터 얻어오기
Author-email: FinPro <finpro1224@gmail.com>
Classifier: Programming Language :: Python :: 3
Classifier: License :: OSI Approved :: MIT License
Classifier: Operating System :: OS Independent
Requires-Python: >=3.8
License-File: LICENSE
Requires-Dist: requests >2
Requires-Dist: pandas >2
